{"frames":{"094_jpg":{"x":1,"y":1,"w":390,"h":260,"offX":0,"offY":0,"sourceW":390,"sourceH":260},"449_jpg":{"x":393,"y":1,"w":390,"h":260,"offX":0,"offY":0,"sourceW":390,"sourceH":260},"093_jpg":{"x":785,"y":1,"w":390,"h":260,"offX":0,"offY":0,"sourceW":390,"sourceH":260},"445_jpg":{"x":1177,"y":1,"w":390,"h":260,"offX":0,"offY":0,"sourceW":390,"sourceH":260},"092_jpg":{"x":1569,"y":1,"w":390,"h":260,"offX":0,"offY":0,"sourceW":390,"sourceH":260},"441_jpg":{"x":1,"y":263,"w":390,"h":260,"offX":0,"offY":0,"sourceW":390,"sourceH":260},"091_jpg":{"x":393,"y":263,"w":390,"h":260,"offX":0,"offY":0,"sourceW":390,"sourceH":260},"437_jpg":{"x":785,"y":263,"w":390,"h":260,"offX":0,"offY":0,"sourceW":390,"sourceH":260},"090_jpg":{"x":1177,"y":263,"w":390,"h":260,"offX":0,"offY":0,"sourceW":390,"sourceH":260},"433_jpg":{"x":1569,"y":263,"w":390,"h":260,"offX":0,"offY":0,"sourceW":390,"sourceH":260},"089_jpg":{"x":1,"y":525,"w":390,"h":260,"offX":0,"offY":0,"sourceW":390,"sourceH":260},"429_jpg":{"x":393,"y":525,"w":390,"h":260,"offX":0,"offY":0,"sourceW":390,"sourceH":260},"088_jpg":{"x":785,"y":525,"w":390,"h":260,"offX":0,"offY":0,"sourceW":390,"sourceH":260},"425_jpg":{"x":1177,"y":525,"w":390,"h":260,"offX":0,"offY":0,"sourceW":390,"sourceH":260},"087_jpg":{"x":1569,"y":525,"w":390,"h":260,"offX":0,"offY":0,"sourceW":390,"sourceH":260},"421_jpg":{"x":1,"y":787,"w":390,"h":260,"offX":0,"offY":0,"sourceW":390,"sourceH":260},"086_jpg":{"x":393,"y":787,"w":390,"h":260,"offX":0,"offY":0,"sourceW":390,"sourceH":260},"417_jpg":{"x":785,"y":787,"w":390,"h":260,"offX":0,"offY":0,"sourceW":390,"sourceH":260},"085_jpg":{"x":1177,"y":787,"w":390,"h":260,"offX":0,"offY":0,"sourceW":390,"sourceH":260},"413_jpg":{"x":1569,"y":787,"w":390,"h":260,"offX":0,"offY":0,"sourceW":390,"sourceH":260},"084_jpg":{"x":1,"y":1049,"w":390,"h":260,"offX":0,"offY":0,"sourceW":390,"sourceH":260},"409_jpg":{"x":393,"y":1049,"w":390,"h":260,"offX":0,"offY":0,"sourceW":390,"sourceH":260},"083_jpg":{"x":785,"y":1049,"w":390,"h":260,"offX":0,"offY":0,"sourceW":390,"sourceH":260},"405_jpg":{"x":1177,"y":1049,"w":390,"h":260,"offX":0,"offY":0,"sourceW":390,"sourceH":260},"082_jpg":{"x":1569,"y":1049,"w":390,"h":260,"offX":0,"offY":0,"sourceW":390,"sourceH":260},"401_jpg":{"x":1,"y":1311,"w":390,"h":260,"offX":0,"offY":0,"sourceW":390,"sourceH":260},"081_jpg":{"x":393,"y":1311,"w":390,"h":260,"offX":0,"offY":0,"sourceW":390,"sourceH":260},"397_jpg":{"x":785,"y":1311,"w":390,"h":260,"offX":0,"offY":0,"sourceW":390,"sourceH":260},"080_jpg":{"x":1177,"y":1311,"w":390,"h":260,"offX":0,"offY":0,"sourceW":390,"sourceH":260},"393_jpg":{"x":1569,"y":1311,"w":390,"h":260,"offX":0,"offY":0,"sourceW":390,"sourceH":260},"079_jpg":{"x":1,"y":1573,"w":390,"h":260,"offX":0,"offY":0,"sourceW":390,"sourceH":260},"389_jpg":{"x":393,"y":1573,"w":390,"h":260,"offX":0,"offY":0,"sourceW":390,"sourceH":260},"078_jpg":{"x":785,"y":1573,"w":390,"h":260,"offX":0,"offY":0,"sourceW":390,"sourceH":260},"385_jpg":{"x":1177,"y":1573,"w":390,"h":260,"offX":0,"offY":0,"sourceW":390,"sourceH":260},"077_jpg":{"x":1569,"y":1573,"w":390,"h":260,"offX":0,"offY":0,"sourceW":390,"sourceH":260}},"file":"preload-13sheet_6648d467.png"}